vericlient-0.1.6.dist-info/METADATA
vericlient-0.1.6.dist-info/WHEEL
vericlient-0.1.6.dist-info/licenses/LICENSE
vericlient/__init__.py
vericlient/apis.py
vericlient/client.py
vericlient/config/__init__.py
vericlient/config/config.py
vericlient/config/config.yml
vericlient/daspeak/__init__.py
vericlient/daspeak/client.py
vericlient/daspeak/endpoints.py
vericlient/daspeak/exceptions.py
vericlient/daspeak/models.py
vericlient/endpoints.py
vericlient/environments.py
vericlient/exceptions.py
vericlient-0.1.6.dist-info/RECORD
