Metadata-Version: 2.1
Name: vericlient
Version: 0.1.6
Summary: Provides a simple and robust interaction with the Veridas API.
Author-Email: Carlos Larriu <larriucarlos@gmail.com>
License: MIT License
Classifier: Development Status :: 1 - Planning
Classifier: Intended Audience :: Developers
Classifier: License :: OSI Approved :: MIT License
Classifier: Programming Language :: Python
Classifier: Programming Language :: Python :: 3
Classifier: Programming Language :: Python :: 3.10
Project-URL: Homepage, https://clarriu97.github.io/vericlient/
Project-URL: Documentation, https://clarriu97.github.io/vericlient/api_docs/vericlient/
Project-URL: Repository, https://github.com/clarriu97/vericlient
Project-URL: Issues, https://github.com/clarriu97/vericlient/issues
Project-URL: Changelog, https://github.com/clarriu97/vericlient/blob/master/CHANGELOG.md
Requires-Python: >=3.10
Requires-Dist: pydantic>=2.7.4
Requires-Dist: structlog>=24.2.0
Requires-Dist: requests>=2.32.3
Requires-Dist: dynaconf>=3.2.5
Requires-Dist: mkdocs>=1.6.0; extra == "docs"
Requires-Dist: mkdocs-material>=9.5.29; extra == "docs"
Requires-Dist: mkdocstrings[python]>=0.25.1; extra == "docs"
Provides-Extra: docs
